README.md
setup.py
py_cadc/__init__.py
py_cadc/cdc.py
py_cadc/consumer.py
py_cadc/producer.py
py_cadc/watch_cdc.py
py_cadc/watch_mysql.py
pycacd.egg-info/PKG-INFO
pycacd.egg-info/SOURCES.txt
pycacd.egg-info/dependency_links.txt
pycacd.egg-info/requires.txt
pycacd.egg-info/top_level.txt