Metadata-Version: 2.1
Name: pycacd
Version: 0.4.1
Summary: Function library to track changes in SQL server and MySQL databases.
Home-page: https://github.com/trevino-676/pyCaDc
Author: Luis Manuel Torres Trevino
Author-email: lmtorres123@icloud.com
License: UNKNOWN
Platform: UNKNOWN
Classifier: Programming Language :: Python :: 3
Classifier: License :: OSI Approved :: GNU General Public License v3 (GPLv3)
Classifier: Operating System :: OS Independent
Requires-Python: >=3.6
